quant_async/__init__.py
quant_async/algo.py
quant_async/blotter.py
quant_async/broker.py
quant_async/futures.py
quant_async/instrument.py
quant_async/models.py
quant_async/monitoring.py
quant_async/objects.py
quant_async/reports.py
quant_async/tools.py
quant_async/util.py
quant_async/version.py
quant_async-0.2.1.dist-info/licenses/LICENSE
quant_async-0.2.1.dist-info/METADATA
quant_async-0.2.1.dist-info/WHEEL
quant_async-0.2.1.dist-info/top_level.txt
quant_async-0.2.1.dist-info/RECORD
