Metadata-Version: 2.4
Name: quant-async
Version: 0.2.1
Summary: Interactive Brokers Async Trading Framework for Python 3.12+
Author-email: Kelvin Gao <89156201@qq.com>
Maintainer-email: Kelvin Gao <89156201@qq.com>
License-Expression: MIT
Project-URL: Homepage, https://github.com/kelvingao/quant_async
Project-URL: Repository, https://github.com/kelvingao/quant_async.git
Project-URL: Documentation, https://github.com/kelvingao/quant_async#readme
Project-URL: Issues, https://github.com/kelvingao/quant_async/issues
Keywords: trading,interactive-brokers,async,finance,algorithmic-trading
Classifier: Development Status :: 3 - Alpha
Classifier: Intended Audience :: Financial and Insurance Industry
Classifier: Intended Audience :: Developers
Classifier: Operating System :: OS Independent
Classifier: Programming Language :: Python :: 3
Classifier: Programming Language :: Python :: 3.12
Classifier: Topic :: Office/Business :: Financial :: Investment
Requires-Python: >=3.12
License-File: LICENSE
Requires-Dist: aiozmq>=1.0.0
Requires-Dist: asyncpg>=0.30.0
Requires-Dist: beautifulsoup4>=4.13.4
Requires-Dist: bump2version>=1.0.1
Requires-Dist: coverage>=7.10.2
Requires-Dist: ib-async>=0.9.86
Requires-Dist: fastapi>=0.115.12
Requires-Dist: jinja2>=3.1.6
Requires-Dist: msgspec>=0.19.0
Requires-Dist: numpy>=2.3.2
Requires-Dist: pandas>=2.3.1
Requires-Dist: psycopg2>=2.9.10
Requires-Dist: pytest-cov>=6.2.1
Requires-Dist: python-dotenv>=1.1.1
Requires-Dist: requests>=2.32.3
Requires-Dist: uvicorn>=0.30.0
Requires-Dist: twine>=6.1.0
Dynamic: license-file
